prelude_cli/__init__.py
prelude_cli/cli.py
prelude_cli/templates/README.md
prelude_cli/templates/__init__.py
prelude_cli/templates/template.go
prelude_cli/views/__init__.py
prelude_cli/views/auth.py
prelude_cli/views/build.py
prelude_cli/views/configure.py
prelude_cli/views/detect.py
prelude_cli/views/generate.py
prelude_cli/views/iam.py
prelude_cli/views/jobs.py
prelude_cli/views/partner.py
prelude_cli/views/scm.py
prelude_cli/views/shared.py
prelude_cli-2.6.11.dist-info/licenses/LICENSE
prelude_cli-2.6.11.dist-info/METADATA
prelude_cli-2.6.11.dist-info/WHEEL
prelude_cli-2.6.11.dist-info/entry_points.txt
prelude_cli-2.6.11.dist-info/top_level.txt
prelude_cli-2.6.11.dist-info/RECORD
